{"nodes":[{"pos":[209,235],"content":"OnXmlDictionaryReaderClose","needQuote":true,"nodes":[{"content":"OnXmlDictionaryReaderClose","pos":[0,26]}]},{"pos":[1523,1533],"content":"System.Xml","needQuote":true,"nodes":[{"content":"System.Xml","pos":[0,10]}]},{"pos":[1848,1863],"content":"GetMethodInfo()","needQuote":true,"nodes":[{"content":"GetMethodInfo()","pos":[0,15]}]},{"pos":[2032,2045],"content":"GetMethodInfo","needQuote":true,"nodes":[{"content":"GetMethodInfo","pos":[0,13]}]},{"pos":[2130,2131],"content":"(","needQuote":true,"nodes":[{"content":"(","pos":[0,1]}]},{"pos":[2158,2159],"content":")","needQuote":true,"nodes":[{"content":")","pos":[0,1]}]},{"pos":[2266,2279],"content":"GetMethodInfo","needQuote":true,"nodes":[{"content":"GetMethodInfo","pos":[0,13]}]},{"pos":[2364,2365],"content":"(","needQuote":true,"nodes":[{"content":"(","pos":[0,1]}]},{"pos":[2392,2393],"content":")","needQuote":true,"nodes":[{"content":")","pos":[0,1]}]},{"pos":[2649,2668],"content":"XmlDictionaryReader","needQuote":true,"nodes":[{"content":"XmlDictionaryReader","pos":[0,19]}]},{"pos":[2905,2928],"content":"GetMethodInfo(Delegate)","needQuote":true,"nodes":[{"content":"GetMethodInfo(Delegate)","pos":[0,23]}]},{"pos":[3129,3142],"content":"GetMethodInfo","needQuote":true,"nodes":[{"content":"GetMethodInfo","pos":[0,13]}]},{"pos":[3227,3228],"content":"(","needQuote":true,"nodes":[{"content":"(","pos":[0,1]}]},{"pos":[3280,3288],"content":"Delegate","needQuote":true,"nodes":[{"content":"Delegate","pos":[0,8]}]},{"pos":[3350,3351],"content":")","needQuote":true,"nodes":[{"content":")","pos":[0,1]}]},{"pos":[3475,3488],"content":"GetMethodInfo","needQuote":true,"nodes":[{"content":"GetMethodInfo","pos":[0,13]}]},{"pos":[3573,3574],"content":"(","needQuote":true,"nodes":[{"content":"(","pos":[0,1]}]},{"pos":[3626,3634],"content":"Delegate","needQuote":true,"nodes":[{"content":"Delegate","pos":[0,8]}]},{"pos":[3696,3697],"content":")","needQuote":true,"nodes":[{"content":")","pos":[0,1]}]},{"pos":[3983,4010],"content":"RuntimeReflectionExtensions","needQuote":true,"nodes":[{"content":"RuntimeReflectionExtensions","pos":[0,27]}]},{"pos":[4227,4244],"content":"System.Reflection","needQuote":true,"nodes":[{"content":"System.Reflection","pos":[0,17]}]}],"content":"items:\n- uid: System.Xml.OnXmlDictionaryReaderClose\n  commentId: T:System.Xml.OnXmlDictionaryReaderClose\n  id: OnXmlDictionaryReaderClose\n  parent: System.Xml\n  children: []\n  langs:\n  - csharp\n  - vb\n  name: OnXmlDictionaryReaderClose\n  fullName: System.Xml.OnXmlDictionaryReaderClose\n  type: Delegate\n  source:\n    remote:\n      path: src/System.Runtime.Serialization.Xml/ref/System.Runtime.Serialization.Xml.cs\n      branch: master\n      repo: https://github.com/dotnet/corefx.git\n    id: OnXmlDictionaryReaderClose\n    path: src/System.Runtime.Serialization.Xml/ref/System.Runtime.Serialization.Xml.cs\n    startLine: 88\n  assemblies:\n  - System.Runtime.Serialization.Xml\n  namespace: System.Xml\n  summary: \"\\n<p>\\n<strong>delegate</strong> for a callback method when closing the reader.</p>\\n\"\n  syntax:\n    content: public delegate void OnXmlDictionaryReaderClose(XmlDictionaryReader reader);\n    content.vb: Public Delegate Sub OnXmlDictionaryReaderClose(reader As XmlDictionaryReader)\n    parameters:\n    - id: reader\n      type: System.Xml.XmlDictionaryReader\n      description: \"\\n<p>The <xref href=\\\"System.Xml.XmlDictionaryReader\\\" data-throw-if-not-resolved=\\\"false\\\"></xref> that fires the <code>OnClose</code> event.</p>\\n\"\n  modifiers.csharp:\n  - public\n  - delegate\n  modifiers.vb:\n  - Public\n  - Delegate\n  nameWithType: OnXmlDictionaryReaderClose\n  extensionMethods:\n  - System.Delegate.System.Reflection.RuntimeReflectionExtensions.GetMethodInfo\nreferences:\n- uid: System.Xml\n  isExternal: false\n  name: System.Xml\n  fullName: System.Xml\n  commentId: N:System.Xml\n  nameWithType: System.Xml\n- uid: System.Delegate.System.Reflection.RuntimeReflectionExtensions.GetMethodInfo\n  parent: System.Reflection.RuntimeReflectionExtensions\n  definition: System.Reflection.RuntimeReflectionExtensions.GetMethodInfo(System.Delegate)\n  name: GetMethodInfo()\n  fullName: System.Reflection.RuntimeReflectionExtensions.GetMethodInfo()\n  spec.csharp:\n  - uid: System.Reflection.RuntimeReflectionExtensions.GetMethodInfo\n    name: GetMethodInfo\n    fullName: System.Reflection.RuntimeReflectionExtensions.GetMethodInfo\n  - name: (\n    fullName: (\n  - name: )\n    fullName: )\n  spec.vb:\n  - uid: System.Reflection.RuntimeReflectionExtensions.GetMethodInfo\n    name: GetMethodInfo\n    fullName: System.Reflection.RuntimeReflectionExtensions.GetMethodInfo\n  - name: (\n    fullName: (\n  - name: )\n    fullName: )\n  commentId: M:System.Reflection.RuntimeReflectionExtensions.GetMethodInfo(System.Delegate)\n  nameWithType: RuntimeReflectionExtensions.GetMethodInfo()\n- uid: System.Xml.XmlDictionaryReader\n  parent: System.Xml\n  isExternal: false\n  name: XmlDictionaryReader\n  fullName: System.Xml.XmlDictionaryReader\n  commentId: T:System.Xml.XmlDictionaryReader\n  nameWithType: XmlDictionaryReader\n- uid: System.Reflection.RuntimeReflectionExtensions.GetMethodInfo(System.Delegate)\n  isExternal: true\n  name: GetMethodInfo(Delegate)\n  fullName: System.Reflection.RuntimeReflectionExtensions.GetMethodInfo(System.Delegate)\n  spec.csharp:\n  - uid: System.Reflection.RuntimeReflectionExtensions.GetMethodInfo(System.Delegate)\n    name: GetMethodInfo\n    fullName: System.Reflection.RuntimeReflectionExtensions.GetMethodInfo\n  - name: (\n    fullName: (\n  - uid: System.Delegate\n    name: Delegate\n    fullName: System.Delegate\n    isExternal: true\n  - name: )\n    fullName: )\n  spec.vb:\n  - uid: System.Reflection.RuntimeReflectionExtensions.GetMethodInfo(System.Delegate)\n    name: GetMethodInfo\n    fullName: System.Reflection.RuntimeReflectionExtensions.GetMethodInfo\n  - name: (\n    fullName: (\n  - uid: System.Delegate\n    name: Delegate\n    fullName: System.Delegate\n    isExternal: true\n  - name: )\n    fullName: )\n  commentId: M:System.Reflection.RuntimeReflectionExtensions.GetMethodInfo(System.Delegate)\n  nameWithType: RuntimeReflectionExtensions.GetMethodInfo(Delegate)\n- uid: System.Reflection.RuntimeReflectionExtensions\n  parent: System.Reflection\n  isExternal: false\n  name: RuntimeReflectionExtensions\n  fullName: System.Reflection.RuntimeReflectionExtensions\n  commentId: T:System.Reflection.RuntimeReflectionExtensions\n  nameWithType: RuntimeReflectionExtensions\n- uid: System.Reflection\n  isExternal: false\n  name: System.Reflection\n  fullName: System.Reflection\n  commentId: N:System.Reflection\n  nameWithType: System.Reflection\n"}