{"nodes":[{"pos":[427,448],"content":"SqlNullValueException","needQuote":true,"nodes":[{"content":"SqlNullValueException","pos":[0,21]}]},{"pos":[2683,2706],"content":"SqlNullValueException()","needQuote":true,"nodes":[{"content":"SqlNullValueException()","pos":[0,23]}]},{"pos":[3852,3881],"content":"SqlNullValueException(String)","needQuote":true,"nodes":[{"content":"SqlNullValueException(String)","pos":[0,29]}]},{"content":"\\n&lt;p&gt;The message that describes the exception.","pos":[4760,4806],"source":"\\n<p>The message that describes the exception."},{"content":"The caller of this constructor is required to ensure that this string has been localized for the current system culture.&lt;/p&gt;\\n","pos":[4807,4933],"source":" The caller of this constructor is required to ensure that this string has been localized for the current system culture.</p>\\n"},{"pos":[5379,5419],"content":"SqlNullValueException(String, Exception)","needQuote":true,"nodes":[{"content":"SqlNullValueException(String, Exception)","pos":[0,40]}]},{"content":"\\n&lt;p&gt;The message that describes the exception.","pos":[6401,6447],"source":"\\n<p>The message that describes the exception."},{"content":"The caller of this constructor is required to ensure that this string has been localized for the current system culture.","pos":[6448,6568]},{"content":"&lt;/p&gt;\\n","pos":[6569,6575],"source":" </p>\\n"},{"content":"\\n&lt;p&gt;The exception that is the cause of the current exception.","pos":[6638,6700],"source":"\\n<p>The exception that is the cause of the current exception."},{"content":"If the &lt;em&gt;innerException&lt;/em&gt; parameter is not &lt;strong&gt;null&lt;/strong&gt;, the current exception is raised in a &lt;strong&gt;catch&lt;/strong&gt; block that handles the inner exception.","pos":[6701,6871],"source":" If the <em>innerException</em> parameter is not <strong>null</strong>, the current exception is raised in a <strong>catch</strong> block that handles the inner exception."},{"content":"&lt;/p&gt;\\n","pos":[6872,6878],"source":" </p>\\n"},{"pos":[7085,7105],"content":"System.Data.SqlTypes","needQuote":true,"nodes":[{"content":"System.Data.SqlTypes","pos":[0,20]}]},{"pos":[7278,7284],"content":"Object","needQuote":true,"nodes":[{"content":"Object","pos":[0,6]}]},{"pos":[7432,7441],"content":"Exception","needQuote":true,"nodes":[{"content":"Exception","pos":[0,9]}]},{"pos":[7633,7649],"content":"SqlTypeException","needQuote":true,"nodes":[{"content":"SqlTypeException","pos":[0,16]}]},{"pos":[7903,7916],"content":"ISerializable","needQuote":true,"nodes":[{"content":"ISerializable","pos":[0,13]}]},{"pos":[8177,8187],"content":"_Exception","needQuote":true,"nodes":[{"content":"_Exception","pos":[0,10]}]},{"pos":[8422,8440],"content":"GetBaseException()","needQuote":true,"nodes":[{"content":"GetBaseException()","pos":[0,18]}]},{"pos":[8557,8573],"content":"GetBaseException","needQuote":true,"nodes":[{"content":"GetBaseException","pos":[0,16]}]},{"pos":[8632,8633],"content":"(","needQuote":true,"nodes":[{"content":"(","pos":[0,1]}]},{"pos":[8660,8661],"content":")","needQuote":true,"nodes":[{"content":")","pos":[0,1]}]},{"pos":[8742,8758],"content":"GetBaseException","needQuote":true,"nodes":[{"content":"GetBaseException","pos":[0,16]}]},{"pos":[8817,8818],"content":"(","needQuote":true,"nodes":[{"content":"(","pos":[0,1]}]},{"pos":[8845,8846],"content":")","needQuote":true,"nodes":[{"content":")","pos":[0,1]}]},{"pos":[9045,9055],"content":"ToString()","needQuote":true,"nodes":[{"content":"ToString()","pos":[0,10]}]},{"pos":[9156,9164],"content":"ToString","needQuote":true,"nodes":[{"content":"ToString","pos":[0,8]}]},{"pos":[9215,9216],"content":"(","needQuote":true,"nodes":[{"content":"(","pos":[0,1]}]},{"pos":[9243,9244],"content":")","needQuote":true,"nodes":[{"content":")","pos":[0,1]}]},{"pos":[9317,9325],"content":"ToString","needQuote":true,"nodes":[{"content":"ToString","pos":[0,8]}]},{"pos":[9376,9377],"content":"(","needQuote":true,"nodes":[{"content":"(","pos":[0,1]}]},{"pos":[9404,9405],"content":")","needQuote":true,"nodes":[{"content":")","pos":[0,1]}]},{"pos":[9686,9736],"content":"GetObjectData(SerializationInfo, StreamingContext)","needQuote":true,"nodes":[{"content":"GetObjectData(SerializationInfo, StreamingContext)","pos":[0,50]}]},{"pos":[10034,10047],"content":"GetObjectData","needQuote":true,"nodes":[{"content":"GetObjectData","pos":[0,13]}]},{"pos":[10124,10125],"content":"(","needQuote":true,"nodes":[{"content":"(","pos":[0,1]}]},{"pos":[10208,10225],"content":"SerializationInfo","needQuote":true,"nodes":[{"content":"SerializationInfo","pos":[0,17]}]},{"content":",","pos":[10319,10320]},{"pos":[10407,10423],"content":"StreamingContext","needQuote":true,"nodes":[{"content":"StreamingContext","pos":[0,16]}]},{"pos":[10515,10516],"content":")","needQuote":true,"nodes":[{"content":")","pos":[0,1]}]},{"pos":[10688,10701],"content":"GetObjectData","needQuote":true,"nodes":[{"content":"GetObjectData","pos":[0,13]}]},{"pos":[10778,10779],"content":"(","needQuote":true,"nodes":[{"content":"(","pos":[0,1]}]},{"pos":[10862,10879],"content":"SerializationInfo","needQuote":true,"nodes":[{"content":"SerializationInfo","pos":[0,17]}]},{"content":",","pos":[10973,10974]},{"pos":[11061,11077],"content":"StreamingContext","needQuote":true,"nodes":[{"content":"StreamingContext","pos":[0,16]}]},{"pos":[11169,11170],"content":")","needQuote":true,"nodes":[{"content":")","pos":[0,1]}]},{"pos":[11490,11499],"content":"GetType()","needQuote":true,"nodes":[{"content":"GetType()","pos":[0,9]}]},{"pos":[11598,11605],"content":"GetType","needQuote":true,"nodes":[{"content":"GetType","pos":[0,7]}]},{"pos":[11676,11677],"content":"(","needQuote":true,"nodes":[{"content":"(","pos":[0,1]}]},{"pos":[11704,11705],"content":")","needQuote":true,"nodes":[{"content":")","pos":[0,1]}]},{"pos":[11777,11784],"content":"GetType","needQuote":true,"nodes":[{"content":"GetType","pos":[0,7]}]},{"pos":[11855,11856],"content":"(","needQuote":true,"nodes":[{"content":"(","pos":[0,1]}]},{"pos":[11883,11884],"content":")","needQuote":true,"nodes":[{"content":")","pos":[0,1]}]},{"pos":[12064,12071],"content":"Message","needQuote":true,"nodes":[{"content":"Message","pos":[0,7]}]},{"pos":[12267,12271],"content":"Data","needQuote":true,"nodes":[{"content":"Data","pos":[0,4]}]},{"pos":[12468,12482],"content":"InnerException","needQuote":true,"nodes":[{"content":"InnerException","pos":[0,14]}]},{"pos":[12704,12714],"content":"TargetSite","needQuote":true,"nodes":[{"content":"TargetSite","pos":[0,10]}]},{"pos":[12925,12935],"content":"StackTrace","needQuote":true,"nodes":[{"content":"StackTrace","pos":[0,10]}]},{"pos":[13144,13152],"content":"HelpLink","needQuote":true,"nodes":[{"content":"HelpLink","pos":[0,8]}]},{"pos":[13353,13359],"content":"Source","needQuote":true,"nodes":[{"content":"Source","pos":[0,6]}]},{"pos":[13555,13562],"content":"HResult","needQuote":true,"nodes":[{"content":"HResult","pos":[0,7]}]},{"pos":[13773,13793],"content":"SerializeObjectState","needQuote":true,"nodes":[{"content":"SerializeObjectState","pos":[0,20]}]},{"pos":[14038,14052],"content":"Equals(Object)","needQuote":true,"nodes":[{"content":"Equals(Object)","pos":[0,14]}]},{"pos":[14171,14177],"content":"Equals","needQuote":true,"nodes":[{"content":"Equals","pos":[0,6]}]},{"pos":[14244,14245],"content":"(","needQuote":true,"nodes":[{"content":"(","pos":[0,1]}]},{"pos":[14295,14301],"content":"Object","needQuote":true,"nodes":[{"content":"Object","pos":[0,6]}]},{"pos":[14361,14362],"content":")","needQuote":true,"nodes":[{"content":")","pos":[0,1]}]},{"pos":[14445,14451],"content":"Equals","needQuote":true,"nodes":[{"content":"Equals","pos":[0,6]}]},{"pos":[14518,14519],"content":"(","needQuote":true,"nodes":[{"content":"(","pos":[0,1]}]},{"pos":[14569,14575],"content":"Object","needQuote":true,"nodes":[{"content":"Object","pos":[0,6]}]},{"pos":[14635,14636],"content":")","needQuote":true,"nodes":[{"content":")","pos":[0,1]}]},{"pos":[14850,14872],"content":"Equals(Object, Object)","needQuote":true,"nodes":[{"content":"Equals(Object, Object)","pos":[0,22]}]},{"pos":[15020,15026],"content":"Equals","needQuote":true,"nodes":[{"content":"Equals","pos":[0,6]}]},{"pos":[15093,15094],"content":"(","needQuote":true,"nodes":[{"content":"(","pos":[0,1]}]},{"pos":[15144,15150],"content":"Object","needQuote":true,"nodes":[{"content":"Object","pos":[0,6]}]},{"content":",","pos":[15211,15212]},{"pos":[15267,15273],"content":"Object","needQuote":true,"nodes":[{"content":"Object","pos":[0,6]}]},{"pos":[15333,15334],"content":")","needQuote":true,"nodes":[{"content":")","pos":[0,1]}]},{"pos":[15431,15437],"content":"Equals","needQuote":true,"nodes":[{"content":"Equals","pos":[0,6]}]},{"pos":[15504,15505],"content":"(","needQuote":true,"nodes":[{"content":"(","pos":[0,1]}]},{"pos":[15555,15561],"content":"Object","needQuote":true,"nodes":[{"content":"Object","pos":[0,6]}]},{"content":",","pos":[15622,15623]},{"pos":[15678,15684],"content":"Object","needQuote":true,"nodes":[{"content":"Object","pos":[0,6]}]},{"pos":[15744,15745],"content":")","needQuote":true,"nodes":[{"content":")","pos":[0,1]}]},{"pos":[15990,16021],"content":"ReferenceEquals(Object, Object)","needQuote":true,"nodes":[{"content":"ReferenceEquals(Object, Object)","pos":[0,31]}]},{"pos":[16187,16202],"content":"ReferenceEquals","needQuote":true,"nodes":[{"content":"ReferenceEquals","pos":[0,15]}]},{"pos":[16278,16279],"content":"(","needQuote":true,"nodes":[{"content":"(","pos":[0,1]}]},{"pos":[16329,16335],"content":"Object","needQuote":true,"nodes":[{"content":"Object","pos":[0,6]}]},{"content":",","pos":[16396,16397]},{"pos":[16452,16458],"content":"Object","needQuote":true,"nodes":[{"content":"Object","pos":[0,6]}]},{"pos":[16518,16519],"content":")","needQuote":true,"nodes":[{"content":")","pos":[0,1]}]},{"pos":[16625,16640],"content":"ReferenceEquals","needQuote":true,"nodes":[{"content":"ReferenceEquals","pos":[0,15]}]},{"pos":[16716,16717],"content":"(","needQuote":true,"nodes":[{"content":"(","pos":[0,1]}]},{"pos":[16767,16773],"content":"Object","needQuote":true,"nodes":[{"content":"Object","pos":[0,6]}]},{"content":",","pos":[16834,16835]},{"pos":[16890,16896],"content":"Object","needQuote":true,"nodes":[{"content":"Object","pos":[0,6]}]},{"pos":[16956,16957],"content":")","needQuote":true,"nodes":[{"content":")","pos":[0,1]}]},{"pos":[17187,17200],"content":"GetHashCode()","needQuote":true,"nodes":[{"content":"GetHashCode()","pos":[0,13]}]},{"pos":[17301,17312],"content":"GetHashCode","needQuote":true,"nodes":[{"content":"GetHashCode","pos":[0,11]}]},{"pos":[17384,17385],"content":"(","needQuote":true,"nodes":[{"content":"(","pos":[0,1]}]},{"pos":[17412,17413],"content":")","needQuote":true,"nodes":[{"content":")","pos":[0,1]}]},{"pos":[17486,17497],"content":"GetHashCode","needQuote":true,"nodes":[{"content":"GetHashCode","pos":[0,11]}]},{"pos":[17569,17570],"content":"(","needQuote":true,"nodes":[{"content":"(","pos":[0,1]}]},{"pos":[17597,17598],"content":")","needQuote":true,"nodes":[{"content":")","pos":[0,1]}]},{"pos":[17781,17798],"content":"MemberwiseClone()","needQuote":true,"nodes":[{"content":"MemberwiseClone()","pos":[0,17]}]},{"pos":[17907,17922],"content":"MemberwiseClone","needQuote":true,"nodes":[{"content":"MemberwiseClone","pos":[0,15]}]},{"pos":[17998,17999],"content":"(","needQuote":true,"nodes":[{"content":"(","pos":[0,1]}]},{"pos":[18026,18027],"content":")","needQuote":true,"nodes":[{"content":")","pos":[0,1]}]},{"pos":[18104,18119],"content":"MemberwiseClone","needQuote":true,"nodes":[{"content":"MemberwiseClone","pos":[0,15]}]},{"pos":[18195,18196],"content":"(","needQuote":true,"nodes":[{"content":"(","pos":[0,1]}]},{"pos":[18223,18224],"content":")","needQuote":true,"nodes":[{"content":")","pos":[0,1]}]},{"pos":[18369,18375],"content":"System","needQuote":true,"nodes":[{"content":"System","pos":[0,6]}]},{"pos":[18504,18532],"content":"System.Runtime.Serialization","needQuote":true,"nodes":[{"content":"System.Runtime.Serialization","pos":[0,28]}]},{"pos":[18729,18759],"content":"System.Runtime.InteropServices","needQuote":true,"nodes":[{"content":"System.Runtime.InteropServices","pos":[0,30]}]},{"pos":[18962,18968],"content":"String","needQuote":true,"nodes":[{"content":"String","pos":[0,6]}]}],"content":"items:\n- uid: System.Data.SqlTypes.SqlNullValueException\n  commentId: T:System.Data.SqlTypes.SqlNullValueException\n  id: SqlNullValueException\n  parent: System.Data.SqlTypes\n  children:\n  - System.Data.SqlTypes.SqlNullValueException.#ctor\n  - System.Data.SqlTypes.SqlNullValueException.#ctor(System.String)\n  - System.Data.SqlTypes.SqlNullValueException.#ctor(System.String,System.Exception)\n  langs:\n  - csharp\n  - vb\n  name: SqlNullValueException\n  fullName: System.Data.SqlTypes.SqlNullValueException\n  type: Class\n  source:\n    remote:\n      path: src/System.Data.SqlClient/src/System/Data/SqlTypes/SQLUtility.cs\n      branch: master\n      repo: https://github.com/dotnet/corefx.git\n    id: SqlNullValueException\n    path: src/System.Data.SqlClient/src/System/Data/SqlTypes/SQLUtility.cs\n    startLine: 51\n  assemblies:\n  - System.Data.SqlClient\n  namespace: System.Data.SqlTypes\n  summary: \"\\n<p>The exception that is thrown when the <strong>Value</strong> property of a <xref href=\\\"System.Data.SqlTypes\\\" data-throw-if-not-resolved=\\\"false\\\"></xref> structure is set to null.</p>\\n\"\n  syntax:\n    content: 'public sealed class SqlNullValueException : SqlTypeException, ISerializable, _Exception'\n    content.vb: >-\n      Public NotInheritable Class SqlNullValueException\n          Inherits SqlTypeException\n          Implements ISerializable, _Exception\n  inheritance:\n  - System.Object\n  - System.Exception\n  - System.Data.SqlTypes.SqlTypeException\n  implements:\n  - System.Runtime.Serialization.ISerializable\n  - System.Runtime.InteropServices._Exception\n  inheritedMembers:\n  - System.Exception.GetBaseException\n  - System.Exception.ToString\n  - System.Exception.GetObjectData(System.Runtime.Serialization.SerializationInfo,System.Runtime.Serialization.StreamingContext)\n  - System.Exception.GetType\n  - System.Exception.Message\n  - System.Exception.Data\n  - System.Exception.InnerException\n  - System.Exception.TargetSite\n  - System.Exception.StackTrace\n  - System.Exception.HelpLink\n  - System.Exception.Source\n  - System.Exception.HResult\n  - System.Exception.SerializeObjectState\n  - System.Object.Equals(System.Object)\n  - System.Object.Equals(System.Object,System.Object)\n  - System.Object.ReferenceEquals(System.Object,System.Object)\n  - System.Object.GetHashCode\n  - System.Object.MemberwiseClone\n  modifiers.csharp:\n  - public\n  - sealed\n  - class\n  modifiers.vb:\n  - Public\n  - NotInheritable\n  - Class\n  nameWithType: SqlNullValueException\n- uid: System.Data.SqlTypes.SqlNullValueException.#ctor\n  commentId: M:System.Data.SqlTypes.SqlNullValueException.#ctor\n  id: '#ctor'\n  parent: System.Data.SqlTypes.SqlNullValueException\n  langs:\n  - csharp\n  - vb\n  name: SqlNullValueException()\n  fullName: System.Data.SqlTypes.SqlNullValueException.SqlNullValueException()\n  type: Constructor\n  source:\n    remote:\n      path: src/System.Data.SqlClient/src/System/Data/SqlTypes/SQLUtility.cs\n      branch: master\n      repo: https://github.com/dotnet/corefx.git\n    id: .ctor\n    path: src/System.Data.SqlClient/src/System/Data/SqlTypes/SQLUtility.cs\n    startLine: 54\n  assemblies:\n  - System.Data.SqlClient\n  namespace: System.Data.SqlTypes\n  summary: \"\\n<p>Initializes a new instance of the <xref href=\\\"System.Data.SqlTypes.SqlNullValueException\\\" data-throw-if-not-resolved=\\\"false\\\"></xref> class with a system-supplied message that describes the error.</p>\\n\"\n  syntax:\n    content: public SqlNullValueException()\n    content.vb: Public Sub New\n  modifiers.csharp:\n  - public\n  modifiers.vb:\n  - Public\n  nameWithType: SqlNullValueException.SqlNullValueException()\n- uid: System.Data.SqlTypes.SqlNullValueException.#ctor(System.String)\n  commentId: M:System.Data.SqlTypes.SqlNullValueException.#ctor(System.String)\n  id: '#ctor(System.String)'\n  parent: System.Data.SqlTypes.SqlNullValueException\n  langs:\n  - csharp\n  - vb\n  name: SqlNullValueException(String)\n  fullName: System.Data.SqlTypes.SqlNullValueException.SqlNullValueException(System.String)\n  type: Constructor\n  source:\n    remote:\n      path: src/System.Data.SqlClient/src/System/Data/SqlTypes/SQLUtility.cs\n      branch: master\n      repo: https://github.com/dotnet/corefx.git\n    id: .ctor\n    path: src/System.Data.SqlClient/src/System/Data/SqlTypes/SQLUtility.cs\n    startLine: 59\n  assemblies:\n  - System.Data.SqlClient\n  namespace: System.Data.SqlTypes\n  summary: \"\\n<p>Initializes a new instance of the <xref href=\\\"System.Data.SqlTypes.SqlNullValueException\\\" data-throw-if-not-resolved=\\\"false\\\"></xref> class with a specified message that describes the error.</p>\\n\"\n  syntax:\n    content: public SqlNullValueException(string message)\n    content.vb: Public Sub New(message As String)\n    parameters:\n    - id: message\n      type: System.String\n      description: \"\\n<p>The message that describes the exception. The caller of this constructor is required to ensure that this string has been localized for the current system culture.</p>\\n\"\n  modifiers.csharp:\n  - public\n  modifiers.vb:\n  - Public\n  nameWithType: SqlNullValueException.SqlNullValueException(String)\n- uid: System.Data.SqlTypes.SqlNullValueException.#ctor(System.String,System.Exception)\n  commentId: M:System.Data.SqlTypes.SqlNullValueException.#ctor(System.String,System.Exception)\n  id: '#ctor(System.String,System.Exception)'\n  parent: System.Data.SqlTypes.SqlNullValueException\n  langs:\n  - csharp\n  - vb\n  name: SqlNullValueException(String, Exception)\n  fullName: System.Data.SqlTypes.SqlNullValueException.SqlNullValueException(System.String, System.Exception)\n  type: Constructor\n  source:\n    remote:\n      path: src/System.Data.SqlClient/src/System/Data/SqlTypes/SQLUtility.cs\n      branch: master\n      repo: https://github.com/dotnet/corefx.git\n    id: .ctor\n    path: src/System.Data.SqlClient/src/System/Data/SqlTypes/SQLUtility.cs\n    startLine: 63\n  assemblies:\n  - System.Data.SqlClient\n  namespace: System.Data.SqlTypes\n  summary: \"\\n<p>Initializes a new instance of the <xref href=\\\"System.Data.SqlTypes.SqlNullValueException\\\" data-throw-if-not-resolved=\\\"false\\\"></xref> class with a specified error message and a reference to the inner exception that is the cause of this exception.</p>\\n\"\n  syntax:\n    content: public SqlNullValueException(string message, Exception e)\n    content.vb: Public Sub New(message As String, e As Exception)\n    parameters:\n    - id: message\n      type: System.String\n      description: \"\\n<p>The message that describes the exception. The caller of this constructor is required to ensure that this string has been localized for the current system culture. </p>\\n\"\n    - id: e\n      type: System.Exception\n      description: \"\\n<p>The exception that is the cause of the current exception. If the <em>innerException</em> parameter is not <strong>null</strong>, the current exception is raised in a <strong>catch</strong> block that handles the inner exception. </p>\\n\"\n  modifiers.csharp:\n  - public\n  modifiers.vb:\n  - Public\n  nameWithType: SqlNullValueException.SqlNullValueException(String, Exception)\nreferences:\n- uid: System.Data.SqlTypes\n  isExternal: false\n  name: System.Data.SqlTypes\n  fullName: System.Data.SqlTypes\n  nameWithType: System.Data.SqlTypes\n  commentId: N:System.Data.SqlTypes\n- uid: System.Object\n  parent: System\n  isExternal: false\n  name: Object\n  fullName: System.Object\n  nameWithType: Object\n  commentId: T:System.Object\n- uid: System.Exception\n  parent: System\n  isExternal: false\n  name: Exception\n  fullName: System.Exception\n  nameWithType: Exception\n  commentId: T:System.Exception\n- uid: System.Data.SqlTypes.SqlTypeException\n  parent: System.Data.SqlTypes\n  isExternal: false\n  name: SqlTypeException\n  fullName: System.Data.SqlTypes.SqlTypeException\n  nameWithType: SqlTypeException\n  commentId: T:System.Data.SqlTypes.SqlTypeException\n- uid: System.Runtime.Serialization.ISerializable\n  parent: System.Runtime.Serialization\n  isExternal: false\n  name: ISerializable\n  fullName: System.Runtime.Serialization.ISerializable\n  nameWithType: ISerializable\n  commentId: T:System.Runtime.Serialization.ISerializable\n- uid: System.Runtime.InteropServices._Exception\n  parent: System.Runtime.InteropServices\n  isExternal: true\n  name: _Exception\n  fullName: System.Runtime.InteropServices._Exception\n  nameWithType: _Exception\n  commentId: T:System.Runtime.InteropServices._Exception\n- uid: System.Exception.GetBaseException\n  parent: System.Exception\n  isExternal: false\n  name: GetBaseException()\n  fullName: System.Exception.GetBaseException()\n  spec.csharp:\n  - uid: System.Exception.GetBaseException\n    name: GetBaseException\n    fullName: System.Exception.GetBaseException\n  - name: (\n    fullName: (\n  - name: )\n    fullName: )\n  spec.vb:\n  - uid: System.Exception.GetBaseException\n    name: GetBaseException\n    fullName: System.Exception.GetBaseException\n  - name: (\n    fullName: (\n  - name: )\n    fullName: )\n  nameWithType: Exception.GetBaseException()\n  commentId: M:System.Exception.GetBaseException\n- uid: System.Exception.ToString\n  parent: System.Exception\n  isExternal: false\n  name: ToString()\n  fullName: System.Exception.ToString()\n  spec.csharp:\n  - uid: System.Exception.ToString\n    name: ToString\n    fullName: System.Exception.ToString\n  - name: (\n    fullName: (\n  - name: )\n    fullName: )\n  spec.vb:\n  - uid: System.Exception.ToString\n    name: ToString\n    fullName: System.Exception.ToString\n  - name: (\n    fullName: (\n  - name: )\n    fullName: )\n  nameWithType: Exception.ToString()\n  commentId: M:System.Exception.ToString\n- uid: System.Exception.GetObjectData(System.Runtime.Serialization.SerializationInfo,System.Runtime.Serialization.StreamingContext)\n  parent: System.Exception\n  isExternal: true\n  name: GetObjectData(SerializationInfo, StreamingContext)\n  fullName: System.Exception.GetObjectData(System.Runtime.Serialization.SerializationInfo, System.Runtime.Serialization.StreamingContext)\n  spec.csharp:\n  - uid: System.Exception.GetObjectData(System.Runtime.Serialization.SerializationInfo,System.Runtime.Serialization.StreamingContext)\n    name: GetObjectData\n    fullName: System.Exception.GetObjectData\n    isExternal: true\n  - name: (\n    fullName: (\n  - uid: System.Runtime.Serialization.SerializationInfo\n    name: SerializationInfo\n    fullName: System.Runtime.Serialization.SerializationInfo\n    isExternal: true\n  - name: ', '\n    fullName: ', '\n  - uid: System.Runtime.Serialization.StreamingContext\n    name: StreamingContext\n    fullName: System.Runtime.Serialization.StreamingContext\n    isExternal: true\n  - name: )\n    fullName: )\n  spec.vb:\n  - uid: System.Exception.GetObjectData(System.Runtime.Serialization.SerializationInfo,System.Runtime.Serialization.StreamingContext)\n    name: GetObjectData\n    fullName: System.Exception.GetObjectData\n    isExternal: true\n  - name: (\n    fullName: (\n  - uid: System.Runtime.Serialization.SerializationInfo\n    name: SerializationInfo\n    fullName: System.Runtime.Serialization.SerializationInfo\n    isExternal: true\n  - name: ', '\n    fullName: ', '\n  - uid: System.Runtime.Serialization.StreamingContext\n    name: StreamingContext\n    fullName: System.Runtime.Serialization.StreamingContext\n    isExternal: true\n  - name: )\n    fullName: )\n  nameWithType: Exception.GetObjectData(SerializationInfo, StreamingContext)\n  commentId: M:System.Exception.GetObjectData(System.Runtime.Serialization.SerializationInfo,System.Runtime.Serialization.StreamingContext)\n- uid: System.Exception.GetType\n  parent: System.Exception\n  isExternal: true\n  name: GetType()\n  fullName: System.Exception.GetType()\n  spec.csharp:\n  - uid: System.Exception.GetType\n    name: GetType\n    fullName: System.Exception.GetType\n    isExternal: true\n  - name: (\n    fullName: (\n  - name: )\n    fullName: )\n  spec.vb:\n  - uid: System.Exception.GetType\n    name: GetType\n    fullName: System.Exception.GetType\n    isExternal: true\n  - name: (\n    fullName: (\n  - name: )\n    fullName: )\n  nameWithType: Exception.GetType()\n  commentId: M:System.Exception.GetType\n- uid: System.Exception.Message\n  parent: System.Exception\n  isExternal: false\n  name: Message\n  fullName: System.Exception.Message\n  nameWithType: Exception.Message\n  commentId: P:System.Exception.Message\n- uid: System.Exception.Data\n  parent: System.Exception\n  isExternal: false\n  name: Data\n  fullName: System.Exception.Data\n  nameWithType: Exception.Data\n  commentId: P:System.Exception.Data\n- uid: System.Exception.InnerException\n  parent: System.Exception\n  isExternal: false\n  name: InnerException\n  fullName: System.Exception.InnerException\n  nameWithType: Exception.InnerException\n  commentId: P:System.Exception.InnerException\n- uid: System.Exception.TargetSite\n  parent: System.Exception\n  isExternal: true\n  name: TargetSite\n  fullName: System.Exception.TargetSite\n  nameWithType: Exception.TargetSite\n  commentId: P:System.Exception.TargetSite\n- uid: System.Exception.StackTrace\n  parent: System.Exception\n  isExternal: false\n  name: StackTrace\n  fullName: System.Exception.StackTrace\n  nameWithType: Exception.StackTrace\n  commentId: P:System.Exception.StackTrace\n- uid: System.Exception.HelpLink\n  parent: System.Exception\n  isExternal: false\n  name: HelpLink\n  fullName: System.Exception.HelpLink\n  nameWithType: Exception.HelpLink\n  commentId: P:System.Exception.HelpLink\n- uid: System.Exception.Source\n  parent: System.Exception\n  isExternal: false\n  name: Source\n  fullName: System.Exception.Source\n  nameWithType: Exception.Source\n  commentId: P:System.Exception.Source\n- uid: System.Exception.HResult\n  parent: System.Exception\n  isExternal: false\n  name: HResult\n  fullName: System.Exception.HResult\n  nameWithType: Exception.HResult\n  commentId: P:System.Exception.HResult\n- uid: System.Exception.SerializeObjectState\n  parent: System.Exception\n  isExternal: true\n  name: SerializeObjectState\n  fullName: System.Exception.SerializeObjectState\n  nameWithType: Exception.SerializeObjectState\n  commentId: E:System.Exception.SerializeObjectState\n- uid: System.Object.Equals(System.Object)\n  parent: System.Object\n  isExternal: true\n  name: Equals(Object)\n  fullName: System.Object.Equals(System.Object)\n  spec.csharp:\n  - uid: System.Object.Equals(System.Object)\n    name: Equals\n    fullName: System.Object.Equals\n    isExternal: true\n  - name: (\n    fullName: (\n  - uid: System.Object\n    name: Object\n    fullName: System.Object\n    isExternal: true\n  - name: )\n    fullName: )\n  spec.vb:\n  - uid: System.Object.Equals(System.Object)\n    name: Equals\n    fullName: System.Object.Equals\n    isExternal: true\n  - name: (\n    fullName: (\n  - uid: System.Object\n    name: Object\n    fullName: System.Object\n    isExternal: true\n  - name: )\n    fullName: )\n  nameWithType: Object.Equals(Object)\n  commentId: M:System.Object.Equals(System.Object)\n- uid: System.Object.Equals(System.Object,System.Object)\n  parent: System.Object\n  isExternal: true\n  name: Equals(Object, Object)\n  fullName: System.Object.Equals(System.Object, System.Object)\n  spec.csharp:\n  - uid: System.Object.Equals(System.Object,System.Object)\n    name: Equals\n    fullName: System.Object.Equals\n    isExternal: true\n  - name: (\n    fullName: (\n  - uid: System.Object\n    name: Object\n    fullName: System.Object\n    isExternal: true\n  - name: ', '\n    fullName: ', '\n  - uid: System.Object\n    name: Object\n    fullName: System.Object\n    isExternal: true\n  - name: )\n    fullName: )\n  spec.vb:\n  - uid: System.Object.Equals(System.Object,System.Object)\n    name: Equals\n    fullName: System.Object.Equals\n    isExternal: true\n  - name: (\n    fullName: (\n  - uid: System.Object\n    name: Object\n    fullName: System.Object\n    isExternal: true\n  - name: ', '\n    fullName: ', '\n  - uid: System.Object\n    name: Object\n    fullName: System.Object\n    isExternal: true\n  - name: )\n    fullName: )\n  nameWithType: Object.Equals(Object, Object)\n  commentId: M:System.Object.Equals(System.Object,System.Object)\n- uid: System.Object.ReferenceEquals(System.Object,System.Object)\n  parent: System.Object\n  isExternal: true\n  name: ReferenceEquals(Object, Object)\n  fullName: System.Object.ReferenceEquals(System.Object, System.Object)\n  spec.csharp:\n  - uid: System.Object.ReferenceEquals(System.Object,System.Object)\n    name: ReferenceEquals\n    fullName: System.Object.ReferenceEquals\n    isExternal: true\n  - name: (\n    fullName: (\n  - uid: System.Object\n    name: Object\n    fullName: System.Object\n    isExternal: true\n  - name: ', '\n    fullName: ', '\n  - uid: System.Object\n    name: Object\n    fullName: System.Object\n    isExternal: true\n  - name: )\n    fullName: )\n  spec.vb:\n  - uid: System.Object.ReferenceEquals(System.Object,System.Object)\n    name: ReferenceEquals\n    fullName: System.Object.ReferenceEquals\n    isExternal: true\n  - name: (\n    fullName: (\n  - uid: System.Object\n    name: Object\n    fullName: System.Object\n    isExternal: true\n  - name: ', '\n    fullName: ', '\n  - uid: System.Object\n    name: Object\n    fullName: System.Object\n    isExternal: true\n  - name: )\n    fullName: )\n  nameWithType: Object.ReferenceEquals(Object, Object)\n  commentId: M:System.Object.ReferenceEquals(System.Object,System.Object)\n- uid: System.Object.GetHashCode\n  parent: System.Object\n  isExternal: true\n  name: GetHashCode()\n  fullName: System.Object.GetHashCode()\n  spec.csharp:\n  - uid: System.Object.GetHashCode\n    name: GetHashCode\n    fullName: System.Object.GetHashCode\n    isExternal: true\n  - name: (\n    fullName: (\n  - name: )\n    fullName: )\n  spec.vb:\n  - uid: System.Object.GetHashCode\n    name: GetHashCode\n    fullName: System.Object.GetHashCode\n    isExternal: true\n  - name: (\n    fullName: (\n  - name: )\n    fullName: )\n  nameWithType: Object.GetHashCode()\n  commentId: M:System.Object.GetHashCode\n- uid: System.Object.MemberwiseClone\n  parent: System.Object\n  isExternal: true\n  name: MemberwiseClone()\n  fullName: System.Object.MemberwiseClone()\n  spec.csharp:\n  - uid: System.Object.MemberwiseClone\n    name: MemberwiseClone\n    fullName: System.Object.MemberwiseClone\n    isExternal: true\n  - name: (\n    fullName: (\n  - name: )\n    fullName: )\n  spec.vb:\n  - uid: System.Object.MemberwiseClone\n    name: MemberwiseClone\n    fullName: System.Object.MemberwiseClone\n    isExternal: true\n  - name: (\n    fullName: (\n  - name: )\n    fullName: )\n  nameWithType: Object.MemberwiseClone()\n  commentId: M:System.Object.MemberwiseClone\n- uid: System\n  isExternal: false\n  name: System\n  fullName: System\n  nameWithType: System\n  commentId: N:System\n- uid: System.Runtime.Serialization\n  isExternal: false\n  name: System.Runtime.Serialization\n  fullName: System.Runtime.Serialization\n  nameWithType: System.Runtime.Serialization\n  commentId: N:System.Runtime.Serialization\n- uid: System.Runtime.InteropServices\n  isExternal: false\n  name: System.Runtime.InteropServices\n  fullName: System.Runtime.InteropServices\n  nameWithType: System.Runtime.InteropServices\n  commentId: N:System.Runtime.InteropServices\n- uid: System.String\n  parent: System\n  isExternal: false\n  name: String\n  fullName: System.String\n  nameWithType: String\n  commentId: T:System.String\n"}