{"nodes":[{"pos":[447,461],"content":"IXmlDictionary","needQuote":true,"nodes":[{"content":"IXmlDictionary","pos":[0,14]}]},{"pos":[1776,1817],"content":"TryLookup(Int32, out XmlDictionaryString)","needQuote":true,"nodes":[{"content":"TryLookup(Int32, out XmlDictionaryString)","pos":[0,41]}]},{"content":"\\n&lt;p&gt;Key to look up.&lt;/p&gt;\\n","pos":[2635,2661],"source":"\\n<p>Key to look up.</p>\\n"},{"content":"\\n&lt;p&gt;\\n&lt;strong&gt;true&lt;/strong&gt; if key is in the dictionary, otherwise &lt;strong&gt;false&lt;/strong&gt;.&lt;/p&gt;\\n","pos":[2997,3094],"source":"\\n<p>\\n<strong>true</strong> if key is in the dictionary, otherwise <strong>false</strong>.</p>\\n"},{"pos":[3727,3769],"content":"TryLookup(String, out XmlDictionaryString)","needQuote":true,"nodes":[{"content":"TryLookup(String, out XmlDictionaryString)","pos":[0,42]}]},{"content":"\\n&lt;p&gt;String value being checked for.&lt;/p&gt;\\n","pos":[4601,4643],"source":"\\n<p>String value being checked for.</p>\\n"},{"content":"\\n&lt;p&gt;\\n&lt;strong&gt;true&lt;/strong&gt; if value is in the dictionary, otherwise &lt;strong&gt;false&lt;/strong&gt;.&lt;/p&gt;\\n","pos":[4949,5048],"source":"\\n<p>\\n<strong>true</strong> if value is in the dictionary, otherwise <strong>false</strong>.</p>\\n"},{"pos":[5736,5791],"content":"TryLookup(XmlDictionaryString, out XmlDictionaryString)","needQuote":true,"nodes":[{"content":"TryLookup(XmlDictionaryString, out XmlDictionaryString)","pos":[0,55]}]},{"pos":[7799,7809],"content":"System.Xml","needQuote":true,"nodes":[{"content":"System.Xml","pos":[0,10]}]},{"pos":[7951,7956],"content":"Int32","needQuote":true,"nodes":[{"content":"Int32","pos":[0,5]}]},{"pos":[8119,8138],"content":"XmlDictionaryString","needQuote":true,"nodes":[{"content":"XmlDictionaryString","pos":[0,19]}]},{"pos":[8331,8338],"content":"Boolean","needQuote":true,"nodes":[{"content":"Boolean","pos":[0,7]}]},{"pos":[8462,8468],"content":"System","needQuote":true,"nodes":[{"content":"System","pos":[0,6]}]},{"pos":[8599,8605],"content":"String","needQuote":true,"nodes":[{"content":"String","pos":[0,6]}]}],"content":"items:\n- uid: System.Xml.IXmlDictionary\n  commentId: T:System.Xml.IXmlDictionary\n  id: IXmlDictionary\n  parent: System.Xml\n  children:\n  - System.Xml.IXmlDictionary.TryLookup(System.Int32,System.Xml.XmlDictionaryString@)\n  - System.Xml.IXmlDictionary.TryLookup(System.String,System.Xml.XmlDictionaryString@)\n  - System.Xml.IXmlDictionary.TryLookup(System.Xml.XmlDictionaryString,System.Xml.XmlDictionaryString@)\n  langs:\n  - csharp\n  - vb\n  name: IXmlDictionary\n  fullName: System.Xml.IXmlDictionary\n  type: Interface\n  source:\n    remote:\n      path: src/System.Runtime.Serialization.Xml/ref/System.Runtime.Serialization.Xml.cs\n      branch: master\n      repo: https://github.com/dotnet/corefx.git\n    id: IXmlDictionary\n    path: src/System.Runtime.Serialization.Xml/ref/System.Runtime.Serialization.Xml.cs\n    startLine: 82\n  assemblies:\n  - System.Runtime.Serialization.Xml\n  namespace: System.Xml\n  summary: \"\\n<p>An <strong>interface</strong> that defines the contract that an Xml dictionary must implement to be used by <xref href=\\\"System.Xml.XmlDictionaryReader\\\" data-throw-if-not-resolved=\\\"false\\\"></xref> and <xref href=\\\"System.Xml.XmlDictionaryWriter\\\" data-throw-if-not-resolved=\\\"false\\\"></xref> implementations.</p>\\n\"\n  syntax:\n    content: public interface IXmlDictionary\n    content.vb: Public Interface IXmlDictionary\n  modifiers.csharp:\n  - public\n  - interface\n  modifiers.vb:\n  - Public\n  - Interface\n  nameWithType: IXmlDictionary\n- uid: System.Xml.IXmlDictionary.TryLookup(System.Int32,System.Xml.XmlDictionaryString@)\n  commentId: M:System.Xml.IXmlDictionary.TryLookup(System.Int32,System.Xml.XmlDictionaryString@)\n  id: TryLookup(System.Int32,System.Xml.XmlDictionaryString@)\n  parent: System.Xml.IXmlDictionary\n  langs:\n  - csharp\n  - vb\n  name: TryLookup(Int32, out XmlDictionaryString)\n  fullName: System.Xml.IXmlDictionary.TryLookup(System.Int32, out System.Xml.XmlDictionaryString)\n  type: Method\n  source:\n    remote:\n      path: src/System.Runtime.Serialization.Xml/ref/System.Runtime.Serialization.Xml.cs\n      branch: master\n      repo: https://github.com/dotnet/corefx.git\n    id: TryLookup\n    path: src/System.Runtime.Serialization.Xml/ref/System.Runtime.Serialization.Xml.cs\n    startLine: 84\n  assemblies:\n  - System.Runtime.Serialization.Xml\n  namespace: System.Xml\n  summary: \"\\n<p>Attempts to look up an entry in the dictionary.</p>\\n\"\n  syntax:\n    content: bool TryLookup(int key, out XmlDictionaryString result)\n    content.vb: Function TryLookup(key As Integer, ByRef result As XmlDictionaryString) As Boolean\n    parameters:\n    - id: key\n      type: System.Int32\n      description: \"\\n<p>Key to look up.</p>\\n\"\n    - id: result\n      type: System.Xml.XmlDictionaryString\n      description: \"\\n<p>If <em>key</em> is defined, the <xref href=\\\"System.Xml.XmlDictionaryString\\\" data-throw-if-not-resolved=\\\"false\\\"></xref> that is mapped to the key; otherwise <strong>null</strong>.</p>\\n\"\n    return:\n      type: System.Boolean\n      description: \"\\n<p>\\n<strong>true</strong> if key is in the dictionary, otherwise <strong>false</strong>.</p>\\n\"\n  fullName.vb: System.Xml.IXmlDictionary.TryLookup(System.Int32, ByRef System.Xml.XmlDictionaryString)\n  name.vb: TryLookup(Int32, ByRef XmlDictionaryString)\n  nameWithType: IXmlDictionary.TryLookup(Int32, out XmlDictionaryString)\n  nameWithType.vb: IXmlDictionary.TryLookup(Int32, ByRef XmlDictionaryString)\n- uid: System.Xml.IXmlDictionary.TryLookup(System.String,System.Xml.XmlDictionaryString@)\n  commentId: M:System.Xml.IXmlDictionary.TryLookup(System.String,System.Xml.XmlDictionaryString@)\n  id: TryLookup(System.String,System.Xml.XmlDictionaryString@)\n  parent: System.Xml.IXmlDictionary\n  langs:\n  - csharp\n  - vb\n  name: TryLookup(String, out XmlDictionaryString)\n  fullName: System.Xml.IXmlDictionary.TryLookup(System.String, out System.Xml.XmlDictionaryString)\n  type: Method\n  source:\n    remote:\n      path: src/System.Runtime.Serialization.Xml/ref/System.Runtime.Serialization.Xml.cs\n      branch: master\n      repo: https://github.com/dotnet/corefx.git\n    id: TryLookup\n    path: src/System.Runtime.Serialization.Xml/ref/System.Runtime.Serialization.Xml.cs\n    startLine: 85\n  assemblies:\n  - System.Runtime.Serialization.Xml\n  namespace: System.Xml\n  summary: \"\\n<p>Checks the dictionary for a specified string value.</p>\\n\"\n  syntax:\n    content: bool TryLookup(string value, out XmlDictionaryString result)\n    content.vb: Function TryLookup(value As String, ByRef result As XmlDictionaryString) As Boolean\n    parameters:\n    - id: value\n      type: System.String\n      description: \"\\n<p>String value being checked for.</p>\\n\"\n    - id: result\n      type: System.Xml.XmlDictionaryString\n      description: \"\\n<p>The corresponding <xref href=\\\"System.Xml.XmlDictionaryString\\\" data-throw-if-not-resolved=\\\"false\\\"></xref>, if found; otherwise <strong>null</strong>.</p>\\n\"\n    return:\n      type: System.Boolean\n      description: \"\\n<p>\\n<strong>true</strong> if value is in the dictionary, otherwise <strong>false</strong>.</p>\\n\"\n  fullName.vb: System.Xml.IXmlDictionary.TryLookup(System.String, ByRef System.Xml.XmlDictionaryString)\n  name.vb: TryLookup(String, ByRef XmlDictionaryString)\n  nameWithType: IXmlDictionary.TryLookup(String, out XmlDictionaryString)\n  nameWithType.vb: IXmlDictionary.TryLookup(String, ByRef XmlDictionaryString)\n- uid: System.Xml.IXmlDictionary.TryLookup(System.Xml.XmlDictionaryString,System.Xml.XmlDictionaryString@)\n  commentId: M:System.Xml.IXmlDictionary.TryLookup(System.Xml.XmlDictionaryString,System.Xml.XmlDictionaryString@)\n  id: TryLookup(System.Xml.XmlDictionaryString,System.Xml.XmlDictionaryString@)\n  parent: System.Xml.IXmlDictionary\n  langs:\n  - csharp\n  - vb\n  name: TryLookup(XmlDictionaryString, out XmlDictionaryString)\n  fullName: System.Xml.IXmlDictionary.TryLookup(System.Xml.XmlDictionaryString, out System.Xml.XmlDictionaryString)\n  type: Method\n  source:\n    remote:\n      path: src/System.Runtime.Serialization.Xml/ref/System.Runtime.Serialization.Xml.cs\n      branch: master\n      repo: https://github.com/dotnet/corefx.git\n    id: TryLookup\n    path: src/System.Runtime.Serialization.Xml/ref/System.Runtime.Serialization.Xml.cs\n    startLine: 86\n  assemblies:\n  - System.Runtime.Serialization.Xml\n  namespace: System.Xml\n  summary: \"\\n<p>Checks the dictionary for a specified <xref href=\\\"System.Xml.XmlDictionaryString\\\" data-throw-if-not-resolved=\\\"false\\\"></xref>.</p>\\n\"\n  syntax:\n    content: bool TryLookup(XmlDictionaryString value, out XmlDictionaryString result)\n    content.vb: Function TryLookup(value As XmlDictionaryString, ByRef result As XmlDictionaryString) As Boolean\n    parameters:\n    - id: value\n      type: System.Xml.XmlDictionaryString\n      description: \"\\n<p>The <xref href=\\\"System.Xml.XmlDictionaryString\\\" data-throw-if-not-resolved=\\\"false\\\"></xref> being checked for.</p>\\n\"\n    - id: result\n      type: System.Xml.XmlDictionaryString\n      description: \"\\n<p>The matching <xref href=\\\"System.Xml.XmlDictionaryString\\\" data-throw-if-not-resolved=\\\"false\\\"></xref>, if found; otherwise <strong>null</strong>.</p>\\n\"\n    return:\n      type: System.Boolean\n      description: \"\\n<p>\\n<strong>true</strong> if <xref href=\\\"System.Xml.XmlDictionaryString\\\" data-throw-if-not-resolved=\\\"false\\\"></xref> is in the dictionary, otherwise <strong>false</strong>.</p>\\n\"\n  fullName.vb: System.Xml.IXmlDictionary.TryLookup(System.Xml.XmlDictionaryString, ByRef System.Xml.XmlDictionaryString)\n  name.vb: TryLookup(XmlDictionaryString, ByRef XmlDictionaryString)\n  nameWithType: IXmlDictionary.TryLookup(XmlDictionaryString, out XmlDictionaryString)\n  nameWithType.vb: IXmlDictionary.TryLookup(XmlDictionaryString, ByRef XmlDictionaryString)\nreferences:\n- uid: System.Xml\n  isExternal: false\n  name: System.Xml\n  fullName: System.Xml\n  commentId: N:System.Xml\n  nameWithType: System.Xml\n- uid: System.Int32\n  parent: System\n  isExternal: false\n  name: Int32\n  fullName: System.Int32\n  commentId: T:System.Int32\n  nameWithType: Int32\n- uid: System.Xml.XmlDictionaryString\n  parent: System.Xml\n  isExternal: false\n  name: XmlDictionaryString\n  fullName: System.Xml.XmlDictionaryString\n  commentId: T:System.Xml.XmlDictionaryString\n  nameWithType: XmlDictionaryString\n- uid: System.Boolean\n  parent: System\n  isExternal: false\n  name: Boolean\n  fullName: System.Boolean\n  commentId: T:System.Boolean\n  nameWithType: Boolean\n- uid: System\n  isExternal: false\n  name: System\n  fullName: System\n  commentId: N:System\n  nameWithType: System\n- uid: System.String\n  parent: System\n  isExternal: false\n  name: String\n  fullName: System.String\n  commentId: T:System.String\n  nameWithType: String\n"}